odoo/addons/l10n_it_withholding_tax_mis_builder/README.rst
odoo/addons/l10n_it_withholding_tax_mis_builder/__init__.py
odoo/addons/l10n_it_withholding_tax_mis_builder/__manifest__.py
odoo/addons/l10n_it_withholding_tax_mis_builder/init_hook.py
odoo/addons/l10n_it_withholding_tax_mis_builder/i18n/it.po
odoo/addons/l10n_it_withholding_tax_mis_builder/i18n/l10n_it_withholding_tax_mis_builder.pot
odoo/addons/l10n_it_withholding_tax_mis_builder/models/__init__.py
odoo/addons/l10n_it_withholding_tax_mis_builder/models/account_move_line.py
odoo/addons/l10n_it_withholding_tax_mis_builder/models/mis_report_instance.py
odoo/addons/l10n_it_withholding_tax_mis_builder/readme/CONTRIBUTORS.rst
odoo/addons/l10n_it_withholding_tax_mis_builder/readme/DESCRIPTION.rst
odoo/addons/l10n_it_withholding_tax_mis_builder/static/description/icon.png
odoo/addons/l10n_it_withholding_tax_mis_builder/static/description/index.html
odoo/addons/l10n_it_withholding_tax_mis_builder/tests/__init__.py
odoo/addons/l10n_it_withholding_tax_mis_builder/tests/common.py
odoo/addons/l10n_it_withholding_tax_mis_builder/tests/test_report.py
odoo/addons/l10n_it_withholding_tax_mis_builder/views/account_move_line_view.xml
odoo14_addon_l10n_it_withholding_tax_mis_builder-14.0.1.0.1.dev3.dist-info/METADATA
odoo14_addon_l10n_it_withholding_tax_mis_builder-14.0.1.0.1.dev3.dist-info/WHEEL
odoo14_addon_l10n_it_withholding_tax_mis_builder-14.0.1.0.1.dev3.dist-info/top_level.txt
odoo14_addon_l10n_it_withholding_tax_mis_builder-14.0.1.0.1.dev3.dist-info/RECORD
