Metadata-Version: 2.1
Name: odoo14-addon-l10n_it_withholding_tax_mis_builder
Version: 14.0.1.0.1.dev3
Summary: ITA - Ritenute d'acconto - MIS Builder
Home-page: https://github.com/OCA/l10n-italy
Author: PyTech SRL, Odoo Community Association (OCA)
Author-email: support@odoo-community.org
License: AGPL-3
Classifier: Programming Language :: Python
Classifier: Framework :: Odoo
Classifier: Framework :: Odoo :: 14.0
Classifier: License :: OSI Approved :: GNU Affero General Public License v3
Requires-Python: >=3.6
Requires-Dist: odoo14-addon-l10n-it-withholding-tax
Requires-Dist: odoo14-addon-mis-builder
Requires-Dist: odoo<14.1dev,>=14.0a
